pymine/__init__.py
pymine/anomaly.py
pymine/association.py
pymine/classifiers.py
pymine/clustering.py
pymine/evaluation.py
pymine/preprocessing.py
pymine/utils.py
pymine_edu-0.1.0.dist-info/licenses/LICENSE
pymine_edu-0.1.0.dist-info/METADATA
pymine_edu-0.1.0.dist-info/WHEEL
pymine_edu-0.1.0.dist-info/top_level.txt
pymine_edu-0.1.0.dist-info/RECORD
